internet_nlp/__init__.py
internet_nlp/context/__init__.py
internet_nlp/context/qa/__init__.py
internet_nlp/no_context/__init__.py
internet_nlp/no_context/qa/NoContextQA.py
internet_nlp/no_context/qa/__init__.py
internet_nlp/tools/Constants.py
internet_nlp/tools/__init__.py
internet_nlp/tools/data/__init__.py
internet_nlp/tools/data/general_nli/AlotNLI.py
internet_nlp/tools/data/general_nli/__init__.py
internet_nlp/tools/data/general_nli/split_data/__init__.py
internet_nlp/tools/data/general_nli/split_data/combine_data.py
internet_nlp/tools/data/general_nli/split_data/download.py
internet_nlp/tools/data/search/Search.py
internet_nlp/tools/data/search/__init__.py
internet_nlp/tools/ml/__init__.py
internet_nlp/tools/ml/closed_book_qa/ClosedBookQA.py
internet_nlp/tools/ml/closed_book_qa/__init__.py
internet_nlp/tools/ml/nli/Nli.py
internet_nlp/tools/ml/nli/__init__.py
internet_nlp/tools/ml/nli/train_model/__init__.py
internet_nlp/tools/ml/nli/train_model/train_cross_encoder_linkbert_nli.py
internet_nlp/tools/ml/open_book_qa/OpenBookQA.py
internet_nlp/tools/ml/open_book_qa/__init__.py
internet_nlp/tools/ml/open_book_qa/train_model/__init__.py
internet_nlp/tools/ml/open_book_qa/train_model/distilbert_base_uncased_qa/__init__.py
internet_nlp/tools/ml/open_book_qa/train_model/t5_open_book_qa/__init__.py
internet_nlp/tools/ml/sentence_to_question/SentenceToQuestion.py
internet_nlp/tools/ml/sentence_to_question/__init__.py
internet_nlp/tools/ml/summarize/Summarize.py
internet_nlp/tools/ml/summarize/__init__.py
internet_nlp/tools/normalizer/Normalize.py
internet_nlp/tools/normalizer/__init__.py
internet_nlp-0.0.9.dist-info/LICENSE
internet_nlp-0.0.9.dist-info/METADATA
internet_nlp-0.0.9.dist-info/WHEEL
internet_nlp-0.0.9.dist-info/top_level.txt
internet_nlp-0.0.9.dist-info/RECORD
